[
  { "id": "11", "initials": "RO", "name": "Rondônia" },
  { "id": "12", "initials": "AC", "name": "Acre" },
  { "id": "13", "initials": "AM", "name": "Amazonas" },
  { "id": "14", "initials": "RR", "name": "Roraima" },
  { "id": "15", "initials": "PA", "name": "Pará" },
  { "id": "16", "initials": "AP", "name": "Amapá" },
  { "id": "17", "initials": "TO", "name": "Tocantins" },
  { "id": "21", "initials": "MA", "name": "Maranhão" },
  { "id": "22", "initials": "PI", "name": "Piauí" },
  { "id": "23", "initials": "CE", "name": "Ceará" },
  { "id": "24", "initials": "RN", "name": "Rio Grande do Norte" },
  { "id": "25", "initials": "PB", "name": "Paraíba" },
  { "id": "26", "initials": "PE", "name": "Pernambuco" },
  { "id": "27", "initials": "AL", "name": "Alagoas" },
  { "id": "28", "initials": "SE", "name": "Sergipe" },
  { "id": "29", "initials": "BA", "name": "Bahia" },
  { "id": "31", "initials": "MG", "name": "Minas Gerais" },
  { "id": "32", "initials": "ES", "name": "Espírito Santo" },
  { "id": "33", "initials": "RJ", "name": "Rio de Janeiro" },
  { "id": "35", "initials": "SP", "name": "São Paulo" },
  { "id": "41", "initials": "PR", "name": "Paraná" },
  { "id": "42", "initials": "SC", "name": "Santa Catarina" },
  { "id": "43", "initials": "RS", "name": "Rio Grande do Sul" },
  { "id": "50", "initials": "MS", "name": "Mato Grosso do Sul" },
  { "id": "51", "initials": "MT", "name": "Mato Grosso" },
  { "id": "52", "initials": "GO", "name": "Goiás" },
  { "id": "53", "initials": "DF", "name": "Distrito Federal" }
]
